tidaloauth4mopidy/__init__.py
tidaloauth4mopidy/models.py
tidaloauth4mopidy-0.2.0.dist-info/LICENSE
tidaloauth4mopidy-0.2.0.dist-info/METADATA
tidaloauth4mopidy-0.2.0.dist-info/WHEEL
tidaloauth4mopidy-0.2.0.dist-info/top_level.txt
tidaloauth4mopidy-0.2.0.dist-info/RECORD
