Metadata-Version: 2.1
Name: tidaloauth4mopidy
Version: 0.2.0
Summary: Unofficial API for TIDAL music streaming service.
Home-page: https://github.com/quodrum-glas/python-tidal
Author: Thomas Amland
Author-email: thomas.amland@googlemail.com
Maintainer: quodrumglas
Maintainer-email: quodrumglas@email.com
License: LGPL
Platform: UNKNOWN
Classifier: Development Status :: 4 - Beta
Classifier: Intended Audience :: Developers
Classifier: License :: OSI Approved :: GNU Lesser General Public License v3 (LGPLv3)
Classifier: Programming Language :: Python :: 2
Classifier: Programming Language :: Python :: 2.7
Classifier: Programming Language :: Python :: 3
Classifier: Programming Language :: Python :: 3.5
Classifier: Programming Language :: Python :: 3.6
Classifier: Programming Language :: Python :: 3.7
Classifier: Programming Language :: Python :: 3.8
Requires-Dist: requests
